nucom/__init__.py
nucom-0.1.0.dist-info/METADATA
nucom-0.1.0.dist-info/WHEEL
nucom-0.1.0.dist-info/top_level.txt
nucom-0.1.0.dist-info/RECORD
