Metadata-Version: 2.4
Name: nucom
Version: 0.1.0
Summary: Numerical Computing Framework
Author-email: Suresh Neethimohan <mohansuresh333@gmail.com>
License: MIT
Requires-Python: >=3.9
